mtneedlet/__init__.py
mtneedlet/maxima.py
mtneedlet/mt.py
mtneedlet/needlets.py
mtneedlet/tools.py
mtneedlet/version.py
mtneedlet-0.0.5.dist-info/LICENSE
mtneedlet-0.0.5.dist-info/METADATA
mtneedlet-0.0.5.dist-info/WHEEL
mtneedlet-0.0.5.dist-info/top_level.txt
mtneedlet-0.0.5.dist-info/RECORD
