Metadata-Version: 2.1
Name: mtneedlet
Version: 0.0.5
Summary: A Python package for needlet filtering and Multiple Testing
Home-page: UNKNOWN
Author: Javier Carron Duque
Author-email: javier.carron@roma2.infn.it
License: UNKNOWN
Platform: UNKNOWN
Classifier: Programming Language :: Python :: 3
Classifier: License :: OSI Approved :: MIT License
Classifier: Operating System :: OS Independent
Requires-Dist: numpy
Requires-Dist: healpy
Requires-Dist: matplotlib
Requires-Dist: scipy
Requires-Dist: pandas
